simpletodo/__init__.py
simpletodo/gui.py
simpletodo/main.py
simpletodo/model.py
simpletodo/util.py
simpletodo-0.1.9.dist-info/entry_points.txt
simpletodo-0.1.9.dist-info/LICENSE
simpletodo-0.1.9.dist-info/WHEEL
simpletodo-0.1.9.dist-info/METADATA
simpletodo-0.1.9.dist-info/RECORD
