Metadata-Version: 2.1
Name: simpletodo
Version: 0.1.9
Summary: simple-todo: Yet another command line TODO tool (命令行 TODO 工具)
Author-email: ahui <102419@gmail.com>
Requires-Python: >=3.10
Classifier: License :: OSI Approved :: MIT License
Requires-Dist: arrow
Requires-Dist: click
Requires-Dist: appdirs
Requires-Dist: pyperclip
Project-URL: Home, https://github.com/ahui2016/simple-todo
